click_odoo/__init__.py
click_odoo/__main__.py
click_odoo/cli.py
click_odoo/compat.py
click_odoo/console.py
click_odoo/env.py
click_odoo/env_options.py
click_odoo-1.8.0.dist-info/licenses/LICENSE
click_odoo-1.8.0.dist-info/METADATA
click_odoo-1.8.0.dist-info/WHEEL
click_odoo-1.8.0.dist-info/entry_points.txt
click_odoo-1.8.0.dist-info/top_level.txt
click_odoo-1.8.0.dist-info/RECORD
