Metadata-Version: 2.4
Name: click-odoo
Version: 1.8.0
Summary: Beautiful, robust CLI for Odoo
Home-page: http://github.com/acsone/click-odoo
Author: ACSONE SA/NV
Author-email: info@acsone.eu
License: LGPLv3+
Classifier: Development Status :: 5 - Production/Stable
Classifier: Intended Audience :: Developers
Classifier: License :: OSI Approved :: GNU Lesser General Public License v3 or later (LGPLv3+)
Classifier: Programming Language :: Python :: 3.6
Classifier: Programming Language :: Python :: 3.7
Classifier: Programming Language :: Python :: 3.8
Classifier: Programming Language :: Python :: 3.9
Classifier: Programming Language :: Python :: 3.10
Classifier: Framework :: Odoo
Requires-Python: >=3.6
License-File: LICENSE
Requires-Dist: click>=7
Dynamic: author
Dynamic: author-email
Dynamic: classifier
Dynamic: description
Dynamic: home-page
Dynamic: license
Dynamic: license-file
Dynamic: requires-dist
Dynamic: requires-python
Dynamic: summary
